datasette_nteract_data_explorer/__init__.py
datasette_nteract_data_explorer/static/DatasetteDataExplorer.f54d22b8.js
datasette_nteract_data_explorer/static/DatasetteDataExplorer.fa0f38ed.js
datasette_nteract_data_explorer/static/index.53c9d9ad.js
datasette_nteract_data_explorer/static/index.bfd4b775.js
datasette_nteract_data_explorer-0.5.1.dist-info/LICENSE
datasette_nteract_data_explorer-0.5.1.dist-info/METADATA
datasette_nteract_data_explorer-0.5.1.dist-info/WHEEL
datasette_nteract_data_explorer-0.5.1.dist-info/entry_points.txt
datasette_nteract_data_explorer-0.5.1.dist-info/top_level.txt
datasette_nteract_data_explorer-0.5.1.dist-info/RECORD
