Metadata-Version: 2.1
Name: datasette-nteract-data-explorer
Version: 0.5.1
Summary: automatic visual data explorer for datasette
Home-page: https://github.com/hydrosquall/datasette-nteract-data-explorer
Author: Cameron Yick
License: Apache License, Version 2.0
Project-URL: Issues, https://github.com/hydrosquall/datasette-nteract-data-explorer/issues
Project-URL: CI, https://github.com/hydrosquall/datasette-nteract-data-explorer/actions
Project-URL: Changelog, https://github.com/hydrosquall/datasette-nteract-data-explorer/releases
Classifier: Framework :: Datasette
Classifier: License :: OSI Approved :: Apache Software License
Requires-Python: >=3.7
License-File: LICENSE
Requires-Dist: datasette
Provides-Extra: test
Requires-Dist: pytest ; extra == 'test'
Requires-Dist: pytest-asyncio ; extra == 'test'
